{
  "pager": { "page": 1, "pageCount": 1, "total": 17, "pageSize": 50 },
  "indicatorGroups": [
    {
      "id": "oehv9EO3vP7",
      "displayName": "ANC",
      "indicators": [
        { "id": "Uvn6LCg7dVU", "displayName": "Couverture ANC 1" },
        {
          "id": "Lzg9LtG1xg3",
          "displayName": "ANC visits per clinical professional"
        },
        { "id": "Tt5TAvdfdVK", "displayName": "ANC LLITN coverage" },
        { "id": "puykO1tbcdi", "displayName": "ANC TT2 coverage" },
        { "id": "ReUHfIn0pTQ", "displayName": " Taux d'abandon d'ANC 1-3" },
        { "id": "c8fABiNpT0B", "displayName": "ANC IPT 2 Coverage" },
        { "id": "OdiHJayrsKo", "displayName": "Couverture ANC 2" },
        { "id": "AUqdhY4mpvp", "displayName": "ANC => 4 Coverage" },
        { "id": "dwEq7wi6nXV", "displayName": "ANC IPT 1 Coverage" },
        { "id": "sB79w2hiLp8", "displayName": "ANC 3 Coverage" }
      ]
    },
    {
      "id": "Dcl7WiHIXp9",
      "displayName": "Commodities",
      "indicators": [
        { "id": "aRabHjSGuGK", "displayName": "Consumption vs population" }
      ]
    },
    {
      "id": "LWvy9lMdSlH",
      "displayName": "Deliveries",
      "indicators": [
        { "id": "n0GE1ISYrdM", "displayName": "PHU delivery rate (by ANC1)" },
        {
          "id": "elTqMUTRgdk",
          "displayName": "Births attended by skilled health personnel (estimated pregancies)"
        },
        {
          "id": "Q3M7Htpzg1Y",
          "displayName": "PHU delivery rate (by expected pregnancies)"
        },
        {
          "id": "tcs5YGnjiKo",
          "displayName": "Maternal death rate by registered live births"
        },
        {
          "id": "ulgL07PF8rq",
          "displayName": "Births attended by skilled health personnel (registered live births)"
        },
        {
          "id": "EoYar8UxddG",
          "displayName": "PHU delivery rate (by registered live births)"
        }
      ]
    },
    {
      "id": "r5HxQkux3GD",
      "displayName": "Diarrhoea",
      "indicators": [
        {
          "id": "JIVMtpjVZqJ",
          "displayName": "Diarrhoea <5 y incidence rate (%)"
        }
      ]
    },
    {
      "id": "PoTnGN0F2n5",
      "displayName": "Emergency Response",
      "indicators": [
        {
          "id": "EY8gsfEomc0",
          "displayName": "ER Technical support visits Rural Result vs Target"
        },
        {
          "id": "MkXHDfrFRKV",
          "displayName": "ER Children trained on key survival skills Result vs Target"
        },
        {
          "id": "ULW9dQOiiTS",
          "displayName": "ER Teacher training programs designed Result vs Target"
        },
        {
          "id": "ryFBhJdetdM",
          "displayName": "ER Census reports produced Result vs Target"
        },
        {
          "id": "iug406zdfTE",
          "displayName": "ER Technical support visits Result vs Target"
        },
        {
          "id": "qmCKRmVj4WX",
          "displayName": "ER Teacher accommodation constructed Urban Result vs Target"
        },
        {
          "id": "oTOpKabJA1v",
          "displayName": "ER Teachers trained Result vs Target"
        },
        {
          "id": "X2XfzgH4NOR",
          "displayName": "ER Visits in schools Rural Result vs Target"
        }
      ]
    },
    {
      "id": "pKHOV0uwPJk",
      "displayName": "Facility infrastructure",
      "indicators": [
        {
          "id": "DwEVHQvMnDZ",
          "displayName": "Public facilities with access to stable electrical power"
        },
        {
          "id": "vEBapQFZ1AA",
          "displayName": "Public facilities with access to running water"
        },
        {
          "id": "v27b2y9kKh7",
          "displayName": "Public facilities with access to Internet connectivity"
        }
      ]
    },
    {
      "id": "RsvclmONCT3",
      "displayName": "HIV",
      "indicators": [
        {
          "id": "lZZxDlIsvTc",
          "displayName": "VCCT post-test counselling rate"
        }
      ]
    },
    {
      "id": "uFcn6Gs8rTC",
      "displayName": "HIV Care Data Export",
      "indicators": [
        {
          "id": "sMTMkudvLCD",
          "displayName": "HIV: testing and counseling 15-24y"
        },
        {
          "id": "lOiynlltFdy",
          "displayName": "HIV: testing and counseling 25-49y"
        },
        {
          "id": "lI5Q5vkydYu",
          "displayName": "HIV: testing and counseling <15y"
        },
        {
          "id": "btgZ1oeF9pJ",
          "displayName": "HIV: testing and counseling >49y"
        }
      ]
    },
    {
      "id": "srxUNt2w5jn",
      "displayName": "Immunization",
      "indicators": [
        { "id": "n5nS0SmkUpq", "displayName": "OPV 0 Coverage <1y" },
        { "id": "tUIlpyeeX9N", "displayName": "Penta 3 Coverage <1y" },
        { "id": "QsuBK2pMfkk", "displayName": "OPV 2 Coverage <1y" },
        { "id": "Om2QoRtsncL", "displayName": "Penta 2 Coverage <1y" },
        { "id": "FnYCr2EAzWS", "displayName": "BCG Coverage <1y" },
        { "id": "i7WSgSJpnfu", "displayName": "Penta 1 Coverage <1y" },
        { "id": "JoEzWYGdX7s", "displayName": "OPV 3 Coverage <1y" },
        {
          "id": "d9thHOJMROr",
          "displayName": "Dropout rate Penta 1 - Measles"
        },
        { "id": "EdN7qlmI5FS", "displayName": "Dropout rate Penta 1 - 3" },
        { "id": "YlTWksXEhEO", "displayName": "OPV 1 Coverage <1y" },
        { "id": "FbKK4ofIv5R", "displayName": "Measles Coverage <1y" },
        { "id": "eTDtyyaSA7f", "displayName": "FIC <1y" }
      ]
    },
    {
      "id": "VMAd8jORtWW",
      "displayName": "Malaria",
      "indicators": [
        { "id": "nkjlWUMIdHh", "displayName": "Slept under LLITN last night" },
        { "id": "Tt5TAvdfdVK", "displayName": "ANC LLITN coverage" }
      ]
    },
    {
      "id": "ZA6xQWZboe2",
      "displayName": "Nutrition",
      "indicators": [
        {
          "id": "X3taFC1HtE5",
          "displayName": "Exclusive breast feeding at Penta 3"
        },
        { "id": "vKWOc4itBo2", "displayName": "Weight for height <70% rate" },
        { "id": "GQHKiAe3DHR", "displayName": "Weight for height >80% rate" },
        { "id": "nfG18MJZX5o", "displayName": "Weight for height 70-79% rate" }
      ]
    },
    {
      "id": "iSzPwrNnKtX",
      "displayName": "PMTCT",
      "indicators": [
        { "id": "fLbrQ4jEtn6", "displayName": "ZDV at ANC rate" },
        {
          "id": "cTB6uRdmxUB",
          "displayName": "ZDV and 3TC after delivery rate"
        },
        { "id": "vihpFUg2WTy", "displayName": "PMTCT positive test rate" },
        { "id": "GfYjGL16D0W", "displayName": "NVP during labour rate" }
      ]
    },
    {
      "id": "YTeRMLGtger",
      "displayName": "Reproductive Health",
      "indicators": [
        { "id": "Uvn6LCg7dVU", "displayName": "Couverture ANC 1" },
        {
          "id": "elTqMUTRgdk",
          "displayName": "Births attended by skilled health personnel (estimated pregancies)"
        },
        {
          "id": "Q3M7Htpzg1Y",
          "displayName": "PHU delivery rate (by expected pregnancies)"
        },
        {
          "id": "tcs5YGnjiKo",
          "displayName": "Maternal death rate by registered live births"
        },
        { "id": "Tt5TAvdfdVK", "displayName": "ANC LLITN coverage" },
        { "id": "puykO1tbcdi", "displayName": "ANC TT2 coverage" },
        { "id": "Rigf2d2Zbjp", "displayName": "Live births in the PHU" },
        { "id": "ReUHfIn0pTQ", "displayName": " Taux d'abandon d'ANC 1-3" },
        { "id": "c8fABiNpT0B", "displayName": "ANC IPT 2 Coverage" },
        { "id": "OdiHJayrsKo", "displayName": "Couverture ANC 2" },
        { "id": "n0GE1ISYrdM", "displayName": "PHU delivery rate (by ANC1)" },
        {
          "id": "ulgL07PF8rq",
          "displayName": "Births attended by skilled health personnel (registered live births)"
        },
        { "id": "RdkKj1rVp8R", "displayName": "Live births in the community" },
        {
          "id": "EoYar8UxddG",
          "displayName": "PHU delivery rate (by registered live births)"
        },
        { "id": "dwEq7wi6nXV", "displayName": "ANC IPT 1 Coverage" },
        { "id": "sB79w2hiLp8", "displayName": "ANC 3 Coverage" }
      ]
    },
    {
      "id": "LMJd5I0UgHN",
      "displayName": "Service burden",
      "indicators": [
        { "id": "akiT5Ds3gf7", "displayName": "Population per medical doctor" },
        {
          "id": "Lzg9LtG1xg3",
          "displayName": "ANC visits per clinical professional"
        }
      ]
    },
    {
      "id": "EdDc97EJUdd",
      "displayName": "Staffing",
      "indicators": [
        { "id": "akiT5Ds3gf7", "displayName": "Population per medical doctor" },
        {
          "id": "Lzg9LtG1xg3",
          "displayName": "ANC visits per clinical professional"
        }
      ]
    },
    {
      "id": "kjo39T5x7ie",
      "displayName": "Stock",
      "indicators": [
        { "id": "OEWO2PpiUKx", "displayName": "BCG Stock PHU" },
        { "id": "bASXd9ukRGD", "displayName": "OPV Stock PHU" },
        { "id": "loEBZlcsTlx", "displayName": "Measles Stock End Balance" }
      ]
    },
    {
      "id": "PoBSb42oRAw",
      "displayName": "VCCT",
      "indicators": [
        {
          "id": "lZZxDlIsvTc",
          "displayName": "VCCT post-test counselling rate"
        }
      ]
    }
  ]
}
